certbot_azure/__init__.py
certbot_azure/azure_agw.py
certbot_azure/azure_agw_test.py
certbot_azure/dns_azure.py
certbot_azure/dns_azure_test.py
certbot_azure-0.1.0.dist-info/LICENSE.txt
certbot_azure-0.1.0.dist-info/METADATA
certbot_azure-0.1.0.dist-info/WHEEL
certbot_azure-0.1.0.dist-info/entry_points.txt
certbot_azure-0.1.0.dist-info/top_level.txt
certbot_azure-0.1.0.dist-info/RECORD
