Metadata-Version: 2.1
Name: certbot-azure
Version: 0.1.0
Summary: Azure plugin for Certbot client
Home-page: https://github.com/dlapiduz/certbot-azure
Author: Diego Lapiduz
Author-email: diego@lapiduz.com
License: MIT
Keywords: certbot,azure,app_gateway,azure_dns
Platform: UNKNOWN
Classifier: Development Status :: 3 - Alpha
Classifier: Environment :: Plugins
Classifier: Intended Audience :: System Administrators
Classifier: License :: OSI Approved :: Apache Software License
Classifier: Operating System :: POSIX :: Linux
Classifier: Programming Language :: Python
Classifier: Programming Language :: Python :: 3
Classifier: Programming Language :: Python :: 3.7
Classifier: Topic :: Internet :: WWW/HTTP
Classifier: Topic :: Security
Classifier: Topic :: System :: Installation/Setup
Classifier: Topic :: System :: Networking
Classifier: Topic :: System :: Systems Administration
Classifier: Topic :: Utilities
Requires-Dist: acme (>=0.29.0)
Requires-Dist: certbot (>=1.1.0)
Requires-Dist: azure-mgmt-resource
Requires-Dist: azure-mgmt-network
Requires-Dist: azure-mgmt-dns (>=3.0.0)
Requires-Dist: PyOpenSSL (>=19.1.0)
Requires-Dist: setuptools
Requires-Dist: zope.interface
Requires-Dist: mock
